.travis.yml
CHANGES.txt
CONTRIBUTORS.txt
Makefile
README.rst
README.txt
bootstrap.py
buildout.cfg
devel.cfg
setup.py
docs/LICENSE.GPL
docs/LICENSE.txt
local/.travis.yml
local/CHANGES.txt
local/CONTRIBUTORS.txt
local/Makefile
local/README.rst
local/README.txt
local/bootstrap.py
local/buildout.cfg
local/devel.cfg
local/setup.py
local/docs/LICENSE.GPL
local/docs/LICENSE.txt
local/src/plonesocial/__init__.py
local/src/plonesocial/suite/__init__.py
local/src/plonesocial/suite/configure.zcml
local/src/plonesocial/suite/profiles.zcml
local/src/plonesocial/suite/setuphandlers.py
local/src/plonesocial/suite/synci18n.sh
local/src/plonesocial/suite/testing.py
local/src/plonesocial/suite/Extensions/Install.py
local/src/plonesocial/suite/Extensions/__init__.py
local/src/plonesocial/suite/browser/__init__.py
local/src/plonesocial/suite/browser/interfaces.py
local/src/plonesocial/suite/locales/manual.pot
local/src/plonesocial/suite/locales/plonesocial.suite.pot
local/src/plonesocial/suite/locales/en/LC_MESSAGES/plonesocial.suite.po
local/src/plonesocial/suite/locales/es/LC_MESSAGES/plonesocial.suite.po
local/src/plonesocial/suite/locales/nl/LC_MESSAGES/plonesocial.suite.po
local/src/plonesocial/suite/profiles/default/metadata.xml
local/src/plonesocial/suite/profiles/default/plonesocial.suite_various.txt
local/src/plonesocial/suite/profiles/default/portlets.xml
local/src/plonesocial/suite/profiles/default/registry.xml
local/src/plonesocial/suite/profiles/default/types/Document.xml
local/src/plonesocial/suite/profiles/default/types/Event.xml
local/src/plonesocial/suite/profiles/default/types/News_Item.xml
local/src/plonesocial/suite/profiles/demo/metadata.xml
local/src/plonesocial/suite/profiles/demo/plonesocial.suite_demo.txt
local/src/plonesocial/suite/profiles/demo/avatars/admin.jpg
local/src/plonesocial/suite/profiles/demo/avatars/allan_neece.jpg
local/src/plonesocial/suite/profiles/demo/avatars/christian_gast.jpeg
src/plonesocial.suite.egg-info/PKG-INFO
src/plonesocial.suite.egg-info/SOURCES.txt
src/plonesocial.suite.egg-info/dependency_links.txt
src/plonesocial.suite.egg-info/entry_points.txt
src/plonesocial.suite.egg-info/namespace_packages.txt
src/plonesocial.suite.egg-info/not-zip-safe
src/plonesocial.suite.egg-info/requires.txt
src/plonesocial.suite.egg-info/top_level.txt
