Metadata-Version: 1.1
Name: plonesocial.suite
Version: 0.5.3
Summary: Pre-integrated social business suite for Plone
Home-page: http://github.com/cosent/plonesocial.suite
Author: Guido Stevens
Author-email: guido.stevens@cosent.net
License: gpl
Keywords: plone socbiz social microblogging
Platform: UNKNOWN
Classifier: Programming Language :: Python
